pyrcodio/__init__.py
pyrcodio/cli.py
pyrcodio/core.py
pyrcodio/data/attributes_misc.txt
pyrcodio/data/subjects_church.txt
pyrcodio-0.1.0.dist-info/licenses/LICENSE
pyrcodio-0.1.0.dist-info/METADATA
pyrcodio-0.1.0.dist-info/WHEEL
pyrcodio-0.1.0.dist-info/entry_points.txt
pyrcodio-0.1.0.dist-info/top_level.txt
pyrcodio-0.1.0.dist-info/RECORD
