Metadata-Version: 2.4
Name: pyrcodio
Version: 0.1.0
Summary: Una utility CLI blasfema che genera nomi combinando soggetti e attributi.
Home-page: https://github.com/nicoDs96/pyrcodio
Author: Eugenio Del Male
Classifier: Programming Language :: Python :: 3
Classifier: License :: OSI Approved :: MIT License
Classifier: Operating System :: OS Independent
Requires-Python: >=3.6
License-File: LICENSE
Dynamic: author
Dynamic: classifier
Dynamic: description
Dynamic: description-content-type
Dynamic: home-page
Dynamic: license-file
Dynamic: requires-python
Dynamic: summary
